Metadata-Version: 2.1
Name: ter-ver-bb
Version: 0.0
Summary: The Bayes Formula and the Bernoulli Formula
Home-page: UNKNOWN
Author-email: poputnikov-egor1@mail.ru
License: UNKNOWN
Platform: UNKNOWN
